MANIFEST.in
setup.py
qtjq/__init__.py
qtjq/utils.py
qtjq/version.py
qtjq.egg-info/PKG-INFO
qtjq.egg-info/SOURCES.txt
qtjq.egg-info/dependency_links.txt
qtjq.egg-info/not-zip-safe
qtjq.egg-info/requires.txt
qtjq.egg-info/top_level.txt
qtjq/etl/__init__.py
qtjq/etl/factor_info.py
qtjq/etl/factor_values.py
qtjq/etl/industry.py
qtjq/etl/universe.py