Metadata-Version: 2.1
Name: qtjq
Version: 0.0.1
Summary: Quant Trading Related
Home-page: 
Author: Andrew Hu
Author-email: AndrewWeiHu@gmail.com
Platform: any
